reciplanner_cli/__init__.py
reciplanner_cli/__main__.py
reciplanner_cli/kitchen_item.py
reciplanner_cli/kitchen_manager.py
reciplanner_cli/recipe.py
reciplanner_cli/recipe_adder.py
reciplanner_cli-0.12.1.dist-info/LICENSE
reciplanner_cli-0.12.1.dist-info/METADATA
reciplanner_cli-0.12.1.dist-info/WHEEL
reciplanner_cli-0.12.1.dist-info/top_level.txt
reciplanner_cli-0.12.1.dist-info/RECORD
